Metadata-Version: 1.0
Name: mystatistics20221021
Version: 0.0
Summary: Calculate and visuallize, Gaussian, Binomial and Normal distributions
Home-page: UNKNOWN
Author: UNKNOWN
Author-email: billyli1991@gmail.com
License: UNKNOWN
Platform: UNKNOWN
